cat_cafe_sdk/__init__.py
cat_cafe_sdk/client.py
cat_cafe_sdk/py.typed
cat_cafe_sdk-0.1.0.dist-info/METADATA
cat_cafe_sdk-0.1.0.dist-info/WHEEL
cat_cafe_sdk-0.1.0.dist-info/RECORD
