Metadata-Version: 2.4
Name: cat-cafe-sdk
Version: 0.1.0
Summary: Python SDK for CAT Cafe - Continuous Alignment Testing platform for LLM observability
Author-email: Kurtis Seebaldt <kurtisseebaldt@artium.ai>
Requires-Python: >=3.12
Requires-Dist: httpx>=0.24.0
Provides-Extra: dev
Requires-Dist: pytest-asyncio>=0.21.0; extra == 'dev'
Requires-Dist: pytest>=7.0.0; extra == 'dev'
Requires-Dist: respx>=0.20.0; extra == 'dev'
